colorz.py
colorz-1.0.3.dist-info/DESCRIPTION.rst
colorz-1.0.3.dist-info/METADATA
colorz-1.0.3.dist-info/RECORD
colorz-1.0.3.dist-info/WHEEL
colorz-1.0.3.dist-info/entry_points.txt
colorz-1.0.3.dist-info/metadata.json
colorz-1.0.3.dist-info/top_level.txt
