Metadata-Version: 2.0
Name: colorz
Version: 1.0.3
Summary: Color scheme generator.
Home-page: https://github.com/metakirby5/colorz
Author: Ethan Chan
Author-email: metakirby5@gmail.com
License: MIT
Keywords: colorz color scheme theme generator
Platform: UNKNOWN
Classifier: Development Status :: 5 - Production/Stable
Classifier: Environment :: Console
Classifier: Intended Audience :: End Users/Desktop
Classifier: Topic :: Utilities
Classifier: License :: OSI Approved :: MIT License
Classifier: Natural Language :: English
Classifier: Operating System :: POSIX :: Linux
Classifier: Programming Language :: Python :: 2
Classifier: Programming Language :: Python :: 3
Requires-Dist: Pillow
Requires-Dist: scipy
